{
  "name": "Glenn Marshall",
  "age": 48,
  "address": {
    "street": "Garwuf Boulevard",
    "city": "Ekazehvom",
    "state": "KY",
    "zip": "59136"
  },
  "contact": {
    "phone": "(270) 768-2812",
    "servicePhone": "800653953"
  },
  "birthday": "2001-12-22T08:09:51.910Z",
  "ip": "187.190.136.210",
  "foo": "bar",
  "profile": {
    "about": "Hijuso majzud wivaz ja mit voco jazo izenu hiufub kuvpo acifuh onazowi cowevfuf redogul favridaf pe ifiadi ozmilset. Ti ned jizod mu lermec liber logeska ohiji noho mu go ejpiro. Bajo pehrefo uviruf jidutmip we vusuhi uceh dovivukur ajupib dabuzek saimibi sek. Bufjil dezuse hefdagze buce wumu roibcen be rilcuwked wej gewu tudneoj vorwi juzdud ro ku segizno mev civ. Pod zi dim pigaptow ju opesag roj remum sudfuhzab etaovo musub um liteb at zofi. Isizuzo foveb uto warla onegedwod wute bued zirpa etsibvo kanasnen lejsipo nafe ru.",
    "bio": "Ko vebidu tovjezul tewvofzag za raka hanima zelfa su kecba zom dev vuwleztip okjevja ke ec icipep. Nasicu loljiozu son jucacla eleemu zokjedut pemjajef bufagob gawalfo uh izmi co omo tupim samzovwi. Tigo kavbe iz juukalot ponun fahevduz no lu uvi unaije baw gezreh hifluf lukiwa zoidnah ne ileiwu. Warcavec geh penpuc mece gujvitrud rowwite labta hal hap newbelad mi tiodoso. Neero fozwu cen ec viw petapled koroj wahivpa le gohu kusjule ukla jow cez levnajnek wug ke. Tuzgistar oc kowonu sahek ce ca veesveg uhuahcev baz dud riko gecni ahbef uga vuklos cortar hi vubge."
  },
  "apiKey": "b79c272f22f8be4f4ba7de40e5de1746ff7d7982c6189924c728a3fede7b8052",
  "currency": {
    "code": "BMD",
    "name": "Bermuda Dollar"
  }
}