{
  "name": "Raymond Maxwell",
  "age": 19,
  "address": {
    "street": "Gafep Pass",
    "city": "Vubeji",
    "state": "AR",
    "zip": "36592"
  },
  "contact": {
    "phone": "(538) 988-7612",
    "servicePhone": "800414974"
  },
  "birthday": "1974-06-25T20:09:55.519Z",
  "ip": "88.155.122.177",
  "foo": "bar",
  "profile": {
    "about": "Ziadso tuj zahavi jitzajes segukku oz ogeamsoj bepe coh agzihej lewlu wur magokmin guf. De kapzauku tursi lelufet colomge zehsalif okvipow somikba nelebuefi pekuamo gacasolu cahzazinu degup tupi cubruuk wifuvejo pitikmo. Vig ropofko hubur sumcot moz zabobem ohotufu uf roprotad bipij iwuzihdah nivi. Doh heovica kasej golom sorzilu om efzo usbov dadni lauk ve noafoom fipakon.",
    "bio": "Jelumtot hu girtahji gacojeta gavpunvap otkov ro estiw wedce eva re fagkac hi sagpigic uw sef dit. Ecrebus eheoliz gun jemuce bom ala sed degan vumto nujjefve cen vuw voj aruzuw re cuwpof na voizjig. Suwegefo damapkup aj uvnezo moto teawogu jugid zekgotfow gahapo cuwi si me tejbuh garzo seso wedo faag. Ogo piom pe vajcot rujsu gi kero hazzouse ufanez kob ri bolonnap vanipu. Vowoge mus nu bi ruszuiwo je vow ho daali rubipnek lodbophus zemlo jefhuvdo ag de be. Fetgafuv zarsundi edefoha lu zova budeg buzev wam gohi jec powdefrem sej bafkasfah zonid omodok cela. Bus onibauz tohatup zeg honwe poda ijesoen kir raflezza piha zecufi pus neacjem vakagos nab uwmul."
  },
  "apiKey": "c7df60d780ab10166e13c525a24f94b22dc1fe52a11107b3044715737a0f589c",
  "currency": {
    "code": "CZK",
    "name": "Czech Republic Koruna"
  }
}