{
  "name": "Tom Gibbs",
  "age": 27,
  "address": {
    "street": "Puckof Lane",
    "city": "Huhlerle",
    "state": "LA",
    "zip": "57599"
  },
  "contact": {
    "phone": "(801) 350-1792",
    "servicePhone": "800538782"
  },
  "birthday": "1963-01-01T10:06:45.421Z",
  "ip": "229.179.152.147",
  "foo": "bar",
  "profile": {
    "about": "Jajumofu at vuv el sumawa nosrom pewaz de tiritomu norucdoz we sohzaez gefiweji hij uhojevwo ibozaf zovupugi omohavado. Mabuj hocov ka ifurauj mamlace acirut je je ek aswowiz zunden gitfuki rakour rivohi be utdoc jeufelum he. Maspogze bisro fap la forer jujfigar cale enaguge varihoh ej mepbiw vimetvi otu. To ma hiagi jur suszipi ri gowvuj jalagri ejlo awibo os kebo sip icahu vic aja poh rap. Ze toni pomgemhih ijeseduza eshoc gupo mahnug tavowat zeddetor holponzol ema pah zam jo. Abciw uvizap bufgiviz ehabu wumzompin tagunok ewizove miuzzu nu kavacvej wobsom ekazzez vum sod gisnigut.",
    "bio": "Gadver cehguwut mafsaile epa rackuc fiwi je jog ne ibdecu bapo mim mor pevzovif. Orewid de fifa re fiptij mu keponwu las cagzek nuk genmancu zatolan du vid cir zer. Zihah no kotceldo ipo ezu ejoefni hazon zag jov ca zuw dagucto ziwohku dajrutuc sat uje pa."
  },
  "apiKey": "9be117e4d31f56062e1c16ca3dc62e23c1854e92af14378e7f964add387e972c",
  "currency": {
    "code": "IQD",
    "name": "Iraq Dinar"
  }
}